alloniamlops/__init__.py
alloniamlops/compute.py
alloniamlops/configs.py
alloniamlops/seldon.py
alloniamlops-1.0.0.dist-info/METADATA
alloniamlops-1.0.0.dist-info/WHEEL
alloniamlops-1.0.0.dist-info/RECORD
