Metadata-Version: 2.1
Name: alloniamlops
Version: 1.0.0
Summary: Class to deploy AllOnIAModel instances using Seldon
Author: ALLONIA
Requires-Python: >=3.9,<4.0
Classifier: Programming Language :: Python :: 3
Classifier: Programming Language :: Python :: 3.9
Classifier: Programming Language :: Python :: 3.10
Classifier: Programming Language :: Python :: 3.11
Classifier: Programming Language :: Python :: 3.12
Requires-Dist: alloniaconfigs (>=1.1.1,<2.0.0)
Requires-Dist: alloniarest (>=1.2.0,<2.0.0)
